odoo/addons/agreement_rebate/README.rst
odoo/addons/agreement_rebate/__init__.py
odoo/addons/agreement_rebate/__manifest__.py
odoo/addons/agreement_rebate/data/agreement_rebate_data.xml
odoo/addons/agreement_rebate/i18n/agreement_rebate.pot
odoo/addons/agreement_rebate/i18n/es.po
odoo/addons/agreement_rebate/i18n/it.po
odoo/addons/agreement_rebate/i18n/sv.po
odoo/addons/agreement_rebate/models/__init__.py
odoo/addons/agreement_rebate/models/account_move_line.py
odoo/addons/agreement_rebate/models/agreement.py
odoo/addons/agreement_rebate/models/agreement_rebate_settlement.py
odoo/addons/agreement_rebate/models/agreement_type.py
odoo/addons/agreement_rebate/readme/CONTRIBUTORS.md
odoo/addons/agreement_rebate/readme/DESCRIPTION.md
odoo/addons/agreement_rebate/readme/USAGE.md
odoo/addons/agreement_rebate/security/agreement_rebate_security.xml
odoo/addons/agreement_rebate/security/ir.model.access.csv
odoo/addons/agreement_rebate/static/description/icon.png
odoo/addons/agreement_rebate/static/description/index.html
odoo/addons/agreement_rebate/static/img/agreement_discount_global.png
odoo/addons/agreement_rebate/static/img/agreement_discount_line.png
odoo/addons/agreement_rebate/static/img/agreement_discount_section.png
odoo/addons/agreement_rebate/static/img/agreement_discount_section_rule_match.png
odoo/addons/agreement_rebate/static/img/agreement_rebate_lines_filter.png
odoo/addons/agreement_rebate/static/img/create_settlement_invoices.png
odoo/addons/agreement_rebate/static/img/create_settlements_wizard.png
odoo/addons/agreement_rebate/tests/__init__.py
odoo/addons/agreement_rebate/tests/test_agreement_rebate.py
odoo/addons/agreement_rebate/views/agreement_condition_view.xml
odoo/addons/agreement_rebate/views/agreement_menu_view.xml
odoo/addons/agreement_rebate/views/agreement_rebate_settlement_view.xml
odoo/addons/agreement_rebate/views/agreement_type.xml
odoo/addons/agreement_rebate/views/agreement_view.xml
odoo/addons/agreement_rebate/wizards/__init__.py
odoo_addon_agreement_rebate-18.0.1.2.1.dist-info/METADATA
odoo_addon_agreement_rebate-18.0.1.2.1.dist-info/WHEEL
odoo_addon_agreement_rebate-18.0.1.2.1.dist-info/top_level.txt
odoo_addon_agreement_rebate-18.0.1.2.1.dist-info/RECORD
