Metadata-Version: 2.1
Name: odoo-addon-agreement_rebate
Version: 18.0.1.2.1
Requires-Python: >=3.10
Requires-Dist: odoo-addon-account_invoice_refund_link==18.0.*
Requires-Dist: odoo-addon-agreement==18.0.*
Requires-Dist: odoo==18.0.*
Summary: Rebate in agreements
Home-page: https://github.com/OCA/agreement
License: AGPL-3
Author: Tecnativa, Odoo Community Association (OCA)
Author-email: support@odoo-community.org
Classifier: Programming Language :: Python
Classifier: Framework :: Odoo
Classifier: Framework :: Odoo :: 18.0
Classifier: License :: OSI Approved :: GNU Affero General Public License v3
Classifier: Development Status :: 4 - Beta
